Classfile /Users/donghaoyuan/workspaces/IdeaProjects/leetcode/target/classes/com/taldh/unkown/Constructor.class
  Last modified 2020年6月7日; size 844 bytes
  SHA-256 checksum ea00c467d2c54425a96ca4c2cf2c7489935b95f4478332e6207ca016b2d19edc
  Compiled from "Constructor.java"
public class com.taldh.unkown.Constructor
  minor version: 0
  major version: 58
  flags: (0x0021) ACC_PUBLIC, ACC_SUPER
  this_class: #19                         // com/taldh/unkown/Constructor
  super_class: #2                         // java/lang/Object
  interfaces: 0, fields: 1, methods: 2, attributes: 3
Constant pool:
   #1 = Methodref          #2.#3          // java/lang/Object."<init>":()V
   #2 = Class              #4             // java/lang/Object
   #3 = NameAndType        #5:#6          // "<init>":()V
   #4 = Utf8               java/lang/Object
   #5 = Utf8               <init>
   #6 = Utf8               ()V
   #7 = Fieldref           #8.#9          // java/lang/System.out:Ljava/io/PrintStream;
   #8 = Class              #10            // java/lang/System
   #9 = NameAndType        #11:#12        // out:Ljava/io/PrintStream;
  #10 = Utf8               java/lang/System
  #11 = Utf8               out
  #12 = Utf8               Ljava/io/PrintStream;
  #13 = Methodref          #14.#15        // java/io/PrintStream.println:(Ljava/lang/Object;)V
  #14 = Class              #16            // java/io/PrintStream
  #15 = NameAndType        #17:#18        // println:(Ljava/lang/Object;)V
  #16 = Utf8               java/io/PrintStream
  #17 = Utf8               println
  #18 = Utf8               (Ljava/lang/Object;)V
  #19 = Class              #20            // com/taldh/unkown/Constructor
  #20 = Utf8               com/taldh/unkown/Constructor
  #21 = Methodref          #19.#3         // com/taldh/unkown/Constructor."<init>":()V
  #22 = Class              #23            // com/taldh/unkown/Constructor$Test
  #23 = Utf8               com/taldh/unkown/Constructor$Test
  #24 = Methodref          #22.#3         // com/taldh/unkown/Constructor$Test."<init>":()V
  #25 = Class              #26            // com/taldh/unkown/Constructor$Test2
  #26 = Utf8               com/taldh/unkown/Constructor$Test2
  #27 = Methodref          #25.#3         // com/taldh/unkown/Constructor$Test2."<init>":()V
  #28 = Utf8               o
  #29 = Utf8               Ljava/lang/String;
  #30 = Utf8               Code
  #31 = Utf8               LineNumberTable
  #32 = Utf8               LocalVariableTable
  #33 = Utf8               this
  #34 = Utf8               Lcom/taldh/unkown/Constructor;
  #35 = Utf8               main
  #36 = Utf8               ([Ljava/lang/String;)V
  #37 = Utf8               args
  #38 = Utf8               [Ljava/lang/String;
  #39 = Utf8               MethodParameters
  #40 = Utf8               SourceFile
  #41 = Utf8               Constructor.java
  #42 = Utf8               NestMembers
  #43 = Utf8               InnerClasses
  #44 = Utf8               Test
  #45 = Utf8               Test2
{
  java.lang.String o;
    descriptor: Ljava/lang/String;
    flags: (0x0000)

  com.taldh.unkown.Constructor();
    descriptor: ()V
    flags: (0x0000)
    Code:
      stack=2, locals=1, args_size=1
         0: aload_0
         1: invokespecial #1                  // Method java/lang/Object."<init>":()V
         4: getstatic     #7                  // Field java/lang/System.out:Ljava/io/PrintStream;
         7: aload_0
         8: invokevirtual #13                 // Method java/io/PrintStream.println:(Ljava/lang/Object;)V
        11: return
      LineNumberTable:
        line 14: 0
        line 15: 4
        line 16: 11
      LocalVariableTable:
        Start  Length  Slot  Name   Signature
            0      12     0  this   Lcom/taldh/unkown/Constructor;

  public static void main(java.lang.String[]);
    descriptor: ([Ljava/lang/String;)V
    flags: (0x0009) ACC_PUBLIC, ACC_STATIC
    Code:
      stack=3, locals=1, args_size=1
         0: getstatic     #7                  // Field java/lang/System.out:Ljava/io/PrintStream;
         3: new           #19                 // class com/taldh/unkown/Constructor
         6: dup
         7: invokespecial #21                 // Method "<init>":()V
        10: invokevirtual #13                 // Method java/io/PrintStream.println:(Ljava/lang/Object;)V
        13: getstatic     #7                  // Field java/lang/System.out:Ljava/io/PrintStream;
        16: new           #22                 // class com/taldh/unkown/Constructor$Test
        19: dup
        20: invokespecial #24                 // Method com/taldh/unkown/Constructor$Test."<init>":()V
        23: invokevirtual #13                 // Method java/io/PrintStream.println:(Ljava/lang/Object;)V
        26: getstatic     #7                  // Field java/lang/System.out:Ljava/io/PrintStream;
        29: new           #25                 // class com/taldh/unkown/Constructor$Test2
        32: dup
        33: invokespecial #27                 // Method com/taldh/unkown/Constructor$Test2."<init>":()V
        36: invokevirtual #13                 // Method java/io/PrintStream.println:(Ljava/lang/Object;)V
        39: return
      LineNumberTable:
        line 31: 0
        line 32: 13
        line 33: 26
        line 34: 39
      LocalVariableTable:
        Start  Length  Slot  Name   Signature
            0      40     0  args   [Ljava/lang/String;
    MethodParameters:
      Name                           Flags
      args
}
SourceFile: "Constructor.java"
NestMembers:
  com/taldh/unkown/Constructor$Test2
  com/taldh/unkown/Constructor$Test
InnerClasses:
  static #44= #22 of #19;                 // Test=class com/taldh/unkown/Constructor$Test of class com/taldh/unkown/Constructor
  static #45= #25 of #19;                 // Test2=class com/taldh/unkown/Constructor$Test2 of class com/taldh/unkown/Constructor
